cashman/__init__.py
cashman/__main__.py
cashman-0.1.0.dist-info/METADATA
cashman-0.1.0.dist-info/WHEEL
cashman-0.1.0.dist-info/entry_points.txt
cashman-0.1.0.dist-info/top_level.txt
cashman-0.1.0.dist-info/RECORD
