Metadata-Version: 2.1
Name: cashman
Version: 0.1.0
Summary: A cli personal expenses tracker
Home-page: https://github.com/LordUbuntu/cash-man
Author: Jacobus Burger
Author-email: therealjacoburger@gmail.com
License: MIT
Keywords: python,expense tracker,personal finance,finance,cli
Classifier: Development Status :: 2 - Pre-Alpha
Classifier: License :: OSI Approved :: MIT License
Classifier: Programming Language :: Python :: 3.10
Classifier: Operating System :: OS Independent
Classifier: Topic :: Utilities
Classifier: Environment :: Console
Requires-Python: >=3.10
Requires-Dist: rich (==13.3.4)
Requires-Dist: click (==8.1.3)
Requires-Dist: pandas (==1.5.0)
Provides-Extra: dev
Requires-Dist: pytest (>=7.2) ; extra == 'dev'
Requires-Dist: twine (>=4.0.2) ; extra == 'dev'
